{
    "name": "Signin",
    "header": "Welcome Back",
    "ctaText": "Log In",
    "fields": [
        {
            "id": "email",
            "placeholder": "Enter email",
            "type": "text",
            "variant": "Outline",
            "icon": "at-outline"
        },
        {
            "id": "password",
            "placeholder": "Enter password",
            "type": "password",
            "variant": "Outline",
            "icon": "lock-closed-outline"
        }
    ],
    "link": "Don't have account? Sign up for free!",
    "state": {
        "email": "",
        "password": ""
    },
    "validators": {}
}